{
  "meta": {
    "lastUpdated": "2026-01-23T06:29:28.503671",
    "totalCount": 38,
    "screened_from": 1519
  },
  "data": [
    {
      "ticker": "043370",
      "name": "피에이치에이",
      "price": 12070,
      "change_rate": -4.96,
      "breakout_date": "2026-01-19",
      "breakout_price": 12290,
      "volume_ratio": 97.8,
      "ma150": 11346,
      "above_ma150": true,
      "market_cap": 2534,
      "updated_at": "2026-01-23T06:29:28.352439"
    },
    {
      "ticker": "264450",
      "name": "유비쿼스",
      "price": 12290,
      "change_rate": 3.02,
      "breakout_date": "2026-01-21",
      "breakout_price": 10000,
      "volume_ratio": 43.1,
      "ma150": 9017,
      "above_ma150": true,
      "market_cap": 1802,
      "updated_at": "2026-01-23T06:29:28.396901"
    },
    {
      "ticker": "147830",
      "name": "제룡산업",
      "price": 7970,
      "change_rate": -2.57,
      "breakout_date": "2026-01-20",
      "breakout_price": 6890,
      "volume_ratio": 34.6,
      "ma150": 6413,
      "above_ma150": true,
      "market_cap": 1594,
      "updated_at": "2026-01-23T06:29:28.415444"
    },
    {
      "ticker": "047310",
      "name": "파워로직스",
      "price": 6420,
      "change_rate": 3.88,
      "breakout_date": "2026-01-14",
      "breakout_price": 4480,
      "volume_ratio": 33.5,
      "ma150": 4422,
      "above_ma150": true,
      "market_cap": 2350,
      "updated_at": "2026-01-23T06:29:28.361335"
    },
    {
      "ticker": "007860",
      "name": "서연",
      "price": 10630,
      "change_rate": -1.48,
      "breakout_date": "2026-01-16",
      "breakout_price": 10250,
      "volume_ratio": 30.4,
      "ma150": 9720,
      "above_ma150": true,
      "market_cap": 2495,
      "updated_at": "2026-01-23T06:29:28.136900"
    },
    {
      "ticker": "009520",
      "name": "포스코엠텍",
      "price": 18860,
      "change_rate": 3.0,
      "breakout_date": "2026-01-15",
      "breakout_price": 16850,
      "volume_ratio": 21.5,
      "ma150": 14428,
      "above_ma150": true,
      "market_cap": 7853,
      "updated_at": "2026-01-23T06:29:28.275555"
    },
    {
      "ticker": "101330",
      "name": "모베이스",
      "price": 5160,
      "change_rate": -7.36,
      "breakout_date": "2026-01-09",
      "breakout_price": 3390,
      "volume_ratio": 16.5,
      "ma150": 3406,
      "above_ma150": true,
      "market_cap": 1194,
      "updated_at": "2026-01-23T06:29:28.470221"
    },
    {
      "ticker": "047040",
      "name": "대우건설",
      "price": 4970,
      "change_rate": 4.3,
      "breakout_date": "2026-01-16",
      "breakout_price": 3940,
      "volume_ratio": 13.5,
      "ma150": 3831,
      "above_ma150": true,
      "market_cap": 20656,
      "updated_at": "2026-01-23T06:29:28.009374"
    },
    {
      "ticker": "347890",
      "name": "엠투아이",
      "price": 6870,
      "change_rate": -3.65,
      "breakout_date": "2026-01-15",
      "breakout_price": 6870,
      "volume_ratio": 12.0,
      "ma150": 6153,
      "above_ma150": true,
      "market_cap": 1161,
      "updated_at": "2026-01-23T06:29:28.476140"
    },
    {
      "ticker": "024880",
      "name": "케이피에프",
      "price": 6020,
      "change_rate": -6.67,
      "breakout_date": "2026-01-19",
      "breakout_price": 5650,
      "volume_ratio": 11.9,
      "ma150": 5209,
      "above_ma150": true,
      "market_cap": 1204,
      "updated_at": "2026-01-23T06:29:28.467796"
    },
    {
      "ticker": "039560",
      "name": "다산네트웍스",
      "price": 3780,
      "change_rate": 10.2,
      "breakout_date": "2026-01-22",
      "breakout_price": 3425,
      "volume_ratio": 11.7,
      "ma150": 3143,
      "above_ma150": true,
      "market_cap": 1497,
      "updated_at": "2026-01-23T06:29:28.428765"
    },
    {
      "ticker": "003490",
      "name": "대한항공",
      "price": 24100,
      "change_rate": 0.21,
      "breakout_date": "2026-01-16",
      "breakout_price": 23000,
      "volume_ratio": 9.0,
      "ma150": 23105,
      "above_ma150": true,
      "market_cap": 88741,
      "updated_at": "2026-01-23T06:29:27.970274"
    },
    {
      "ticker": "456040",
      "name": "OCI",
      "price": 70900,
      "change_rate": 0.57,
      "breakout_date": "2026-01-14",
      "breakout_price": 63100,
      "volume_ratio": 8.6,
      "ma150": 58610,
      "above_ma150": true,
      "market_cap": 6347,
      "updated_at": "2026-01-23T06:29:28.062209"
    },
    {
      "ticker": "005490",
      "name": "POSCO홀딩스",
      "price": 359500,
      "change_rate": 2.42,
      "breakout_date": "2026-01-13",
      "breakout_price": 327000,
      "volume_ratio": 7.3,
      "ma150": 301783,
      "above_ma150": true,
      "market_cap": 290953,
      "updated_at": "2026-01-23T06:29:27.953393"
    },
    {
      "ticker": "011785",
      "name": "금호석유화학우",
      "price": 70900,
      "change_rate": 0.28,
      "breakout_date": "2026-01-12",
      "breakout_price": 64600,
      "volume_ratio": 7.0,
      "ma150": 60511,
      "above_ma150": true,
      "market_cap": 2143,
      "updated_at": "2026-01-23T06:29:28.157131"
    },
    {
      "ticker": "011780",
      "name": "금호석유화학",
      "price": 145200,
      "change_rate": -0.21,
      "breakout_date": "2026-01-12",
      "breakout_price": 126400,
      "volume_ratio": 5.9,
      "ma150": 116942,
      "above_ma150": true,
      "market_cap": 37798,
      "updated_at": "2026-01-23T06:29:27.990069"
    },
    {
      "ticker": "073490",
      "name": "이노와이어리스",
      "price": 27350,
      "change_rate": -0.73,
      "breakout_date": "2026-01-20",
      "breakout_price": 24850,
      "volume_ratio": 5.3,
      "ma150": 21787,
      "above_ma150": true,
      "market_cap": 2079,
      "updated_at": "2026-01-23T06:29:28.373593"
    },
    {
      "ticker": "126720",
      "name": "수산인더스트리",
      "price": 26150,
      "change_rate": -2.79,
      "breakout_date": "2026-01-14",
      "breakout_price": 22550,
      "volume_ratio": 5.1,
      "ma150": 22739,
      "above_ma150": true,
      "market_cap": 3735,
      "updated_at": "2026-01-23T06:29:28.098030"
    },
    {
      "ticker": "017670",
      "name": "SK텔레콤",
      "price": 61700,
      "change_rate": 1.15,
      "breakout_date": "2026-01-19",
      "breakout_price": 54800,
      "volume_ratio": 4.6,
      "ma150": 54816,
      "above_ma150": true,
      "market_cap": 132525,
      "updated_at": "2026-01-23T06:29:27.965206"
    },
    {
      "ticker": "298020",
      "name": "효성티앤씨",
      "price": 388500,
      "change_rate": 2.37,
      "breakout_date": "2026-01-15",
      "breakout_price": 238000,
      "volume_ratio": 4.6,
      "ma150": 232476,
      "above_ma150": true,
      "market_cap": 16813,
      "updated_at": "2026-01-23T06:29:28.014986"
    },
    {
      "ticker": "006910",
      "name": "보성파워텍",
      "price": 7860,
      "change_rate": -1.87,
      "breakout_date": "2026-01-19",
      "breakout_price": 5820,
      "volume_ratio": 4.6,
      "ma150": 4531,
      "above_ma150": true,
      "market_cap": 3861,
      "updated_at": "2026-01-23T06:29:28.311148"
    },
    {
      "ticker": "004560",
      "name": "현대비앤지스틸",
      "price": 12620,
      "change_rate": 0.88,
      "breakout_date": "2026-01-19",
      "breakout_price": 12130,
      "volume_ratio": 4.5,
      "ma150": 11701,
      "above_ma150": true,
      "market_cap": 1902,
      "updated_at": "2026-01-23T06:29:28.173952"
    },
    {
      "ticker": "251970",
      "name": "펌텍코리아",
      "price": 59500,
      "change_rate": 10.39,
      "breakout_date": "2026-01-22",
      "breakout_price": 56500,
      "volume_ratio": 4.1,
      "ma150": 58414,
      "above_ma150": true,
      "market_cap": 7378,
      "updated_at": "2026-01-23T06:29:28.280330"
    },
    {
      "ticker": "019210",
      "name": "와이지-원",
      "price": 6000,
      "change_rate": 4.71,
      "breakout_date": "2026-01-22",
      "breakout_price": 5750,
      "volume_ratio": 4.1,
      "ma150": 5497,
      "above_ma150": true,
      "market_cap": 2014,
      "updated_at": "2026-01-23T06:29:28.377338"
    },
    {
      "ticker": "023800",
      "name": "인지컨트롤스",
      "price": 7390,
      "change_rate": -0.4,
      "breakout_date": "2026-01-12",
      "breakout_price": 6580,
      "volume_ratio": 4.0,
      "ma150": 6087,
      "above_ma150": true,
      "market_cap": 1168,
      "updated_at": "2026-01-23T06:29:28.229104"
    },
    {
      "ticker": "013570",
      "name": "디와이",
      "price": 5080,
      "change_rate": -2.5,
      "breakout_date": "2026-01-09",
      "breakout_price": 4775,
      "volume_ratio": 3.3,
      "ma150": 4470,
      "above_ma150": true,
      "market_cap": 1337,
      "updated_at": "2026-01-23T06:29:28.212823"
    },
    {
      "ticker": "282330",
      "name": "BGF리테일",
      "price": 119600,
      "change_rate": 2.84,
      "breakout_date": "2026-01-16",
      "breakout_price": 112600,
      "volume_ratio": 3.2,
      "ma150": 112688,
      "above_ma150": true,
      "market_cap": 20671,
      "updated_at": "2026-01-23T06:29:28.008376"
    },
    {
      "ticker": "001120",
      "name": "LX인터내셔널",
      "price": 35850,
      "change_rate": -0.28,
      "breakout_date": "2026-01-15",
      "breakout_price": 34400,
      "volume_ratio": 3.2,
      "ma150": 31476,
      "above_ma150": true,
      "market_cap": 13895,
      "updated_at": "2026-01-23T06:29:28.022134"
    },
    {
      "ticker": "119830",
      "name": "아이텍",
      "price": 6430,
      "change_rate": 1.74,
      "breakout_date": "2026-01-12",
      "breakout_price": 6160,
      "volume_ratio": 2.9,
      "ma150": 5962,
      "above_ma150": true,
      "market_cap": 1504,
      "updated_at": "2026-01-23T06:29:28.426067"
    },
    {
      "ticker": "271560",
      "name": "오리온",
      "price": 115600,
      "change_rate": -1.2,
      "breakout_date": "2026-01-19",
      "breakout_price": 107700,
      "volume_ratio": 2.8,
      "ma150": 107407,
      "above_ma150": true,
      "market_cap": 45703,
      "updated_at": "2026-01-23T06:29:27.983305"
    },
    {
      "ticker": "030610",
      "name": "교보증권",
      "price": 10500,
      "change_rate": 3.55,
      "breakout_date": "2026-01-20",
      "breakout_price": 9970,
      "volume_ratio": 2.8,
      "ma150": 9254,
      "above_ma150": true,
      "market_cap": 11966,
      "updated_at": "2026-01-23T06:29:28.029003"
    },
    {
      "ticker": "058430",
      "name": "포스코스틸리온",
      "price": 40900,
      "change_rate": 2.0,
      "breakout_date": "2026-01-19",
      "breakout_price": 40450,
      "volume_ratio": 2.5,
      "ma150": 39007,
      "above_ma150": true,
      "market_cap": 2454,
      "updated_at": "2026-01-23T06:29:28.140140"
    },
    {
      "ticker": "104830",
      "name": "원익머트리얼즈",
      "price": 36900,
      "change_rate": 6.96,
      "breakout_date": "2026-01-22",
      "breakout_price": 35300,
      "volume_ratio": 2.5,
      "ma150": 28275,
      "above_ma150": true,
      "market_cap": 4652,
      "updated_at": "2026-01-23T06:29:28.299100"
    },
    {
      "ticker": "016740",
      "name": "두올",
      "price": 4080,
      "change_rate": -0.73,
      "breakout_date": "2026-01-21",
      "breakout_price": 4000,
      "volume_ratio": 2.4,
      "ma150": 3587,
      "above_ma150": true,
      "market_cap": 1169,
      "updated_at": "2026-01-23T06:29:28.228264"
    },
    {
      "ticker": "272290",
      "name": "이녹스첨단소재",
      "price": 26850,
      "change_rate": 7.4,
      "breakout_date": "2026-01-22",
      "breakout_price": 25750,
      "volume_ratio": 2.4,
      "ma150": 24319,
      "above_ma150": true,
      "market_cap": 5350,
      "updated_at": "2026-01-23T06:29:28.293685"
    },
    {
      "ticker": "122990",
      "name": "와이솔",
      "price": 6230,
      "change_rate": -1.27,
      "breakout_date": "2026-01-16",
      "breakout_price": 5930,
      "volume_ratio": 2.4,
      "ma150": 5974,
      "above_ma150": true,
      "market_cap": 1659,
      "updated_at": "2026-01-23T06:29:28.407558"
    },
    {
      "ticker": "051600",
      "name": "한전KPS",
      "price": 57800,
      "change_rate": -0.34,
      "breakout_date": "2026-01-19",
      "breakout_price": 54700,
      "volume_ratio": 2.1,
      "ma150": 52354,
      "above_ma150": true,
      "market_cap": 26010,
      "updated_at": "2026-01-23T06:29:27.998349"
    },
    {
      "ticker": "005945",
      "name": "NH투자증권우",
      "price": 20600,
      "change_rate": 1.23,
      "breakout_date": "2026-01-20",
      "breakout_price": 19930,
      "volume_ratio": 2.0,
      "ma150": 18339,
      "above_ma150": true,
      "market_cap": 3887,
      "updated_at": "2026-01-23T06:29:28.095054"
    }
  ]
}